{
  "activityEntities" : [
    "dataSourceCreated",
    [
      {
        "createdDate" : "2026-06-25T06:08:37Z",
        "event" : "dataSourceCreated",
        "id" : "EDE2B4B3-156A-4B1C-8888-14F8B0709A9D",
        "subtitle" : "train_create_ml.csv",
        "title" : "Data Source Created"
      }
    ],
    "dataSourceTrainingStarted",
    [
      {
        "createdDate" : "2026-06-25T06:09:17Z",
        "event" : "dataSourceTrainingStarted",
        "id" : "7EF7C99D-297E-49DA-913F-DE4F4F629C7E",
        "subtitle" : "CodeLaunguageClassifier 1",
        "title" : "Used By"
      },
      {
        "createdDate" : "2026-06-25T06:19:09Z",
        "event" : "dataSourceTrainingStarted",
        "id" : "8010E4EC-5018-43E1-B8E9-7680071D1D61",
        "subtitle" : "CodeLaunguageClassifier 1 copy",
        "title" : "Used By"
      },
      {
        "createdDate" : "2026-06-25T08:32:07Z",
        "event" : "dataSourceTrainingStarted",
        "id" : "7A34D303-B847-43A8-9E6F-5E399CB08DA6",
        "subtitle" : "CodeLaunguageClassifier 1",
        "title" : "Used By"
      },
      {
        "createdDate" : "2026-06-25T09:13:56Z",
        "event" : "dataSourceTrainingStarted",
        "id" : "3BC02390-9F71-4768-9AC1-61E0D324028A",
        "subtitle" : "CodeLaunguageClassifier 1",
        "title" : "Used By"
      },
      {
        "createdDate" : "2026-06-25T09:21:02Z",
        "event" : "dataSourceTrainingStarted",
        "id" : "CDC0B283-E47F-4F65-B02C-F082A3AF2D0B",
        "subtitle" : "CodeLaunguageClassifier 1 copy",
        "title" : "Used By"
      },
      {
        "createdDate" : "2026-06-25T09:24:56Z",
        "event" : "dataSourceTrainingStarted",
        "id" : "5CEA76B1-451B-4221-88E0-DC6A2F4B87D3",
        "subtitle" : "CodeLaunguageClassifier 1 copy 1",
        "title" : "Used By"
      }
    ],
    "dataSourceMetrics",
    [
      {
        "createdDate" : "2026-06-25T06:09:17Z",
        "event" : "dataSourceMetrics",
        "id" : "DAD0E6D6-0E2B-4ED5-88B2-A01DAFE1B0B2",
        "subtitle" : "15 Classes, 582,730 Items",
        "title" : "Data Summary"
      },
      {
        "createdDate" : "2026-06-25T06:19:09Z",
        "event" : "dataSourceMetrics",
        "id" : "023B108F-DCC0-45FD-90BF-30B6451BE3D1",
        "subtitle" : "15 Classes, 582,730 Items",
        "title" : "Data Summary"
      },
      {
        "createdDate" : "2026-06-25T08:32:07Z",
        "event" : "dataSourceMetrics",
        "id" : "252ED022-738F-48B5-A9FD-0A87FED9D9E8",
        "subtitle" : "23 Classes, 878,264 Items",
        "title" : "Data Summary"
      },
      {
        "createdDate" : "2026-06-25T09:13:56Z",
        "event" : "dataSourceMetrics",
        "id" : "6AAA2B28-BCA8-419C-B6CF-D6417D8912EA",
        "subtitle" : "23 Classes, 480,000 Items",
        "title" : "Data Summary"
      },
      {
        "createdDate" : "2026-06-25T09:21:02Z",
        "event" : "dataSourceMetrics",
        "id" : "47CE6E00-F907-4A07-9259-B64E44F92EE1",
        "subtitle" : "23 Classes, 480,000 Items",
        "title" : "Data Summary"
      },
      {
        "createdDate" : "2026-06-25T09:24:56Z",
        "event" : "dataSourceMetrics",
        "id" : "FE439E7A-636C-4217-9164-68CB88147A5F",
        "subtitle" : "23 Classes, 480,000 Items",
        "title" : "Data Summary"
      }
    ]
  ],
  "createdDate" : "2026-06-25T06:08:37Z",
  "dataPathRelativeToProjectURL" : "../CodeTextClassifier/data/train_create_ml.csv/",
  "dataResult" : {
    "classesCount" : 23,
    "createdDate" : "2026-06-25T06:08:37Z",
    "dataAnalysis" : {
      "classifierAnalysis" : {
        "labelStats" : {
          "C" : 20000,
          "C#" : 20000,
          "C++" : 20000,
          "CSS" : 20000,
          "Dart" : 20000,
          "Go" : 20000,
          "HTML" : 20000,
          "JSON" : 20000,
          "Java" : 20000,
          "JavaScript" : 20000,
          "Kotlin" : 20000,
          "Lua" : 20000,
          "Objective-C" : 20000,
          "PHP" : 20000,
          "Python" : 20000,
          "Ruby" : 20000,
          "Rust" : 20000,
          "SQL" : 20000,
          "Shell" : 20000,
          "Swift" : 40000,
          "TypeScript" : 20000,
          "XML" : 20000,
          "YAML" : 20000
        }
      },
      "issues" : [
        {
          "description" : "23 classes found, including Swift, C, HTML",
          "severity" : "debug"
        },
        {
          "description" : "480000 texts found, automatically creating validation set",
          "severity" : "good"
        },
        {
          "description" : "Smallest class is \"YAML\" with 20000 texts",
          "severity" : "debug"
        },
        {
          "description" : "Largest class is \"Swift\" with 40000 text",
          "severity" : "debug"
        }
      ],
      "objectDetectorAnalysis" : {
        "details" : {

        }
      },
      "summary" : {
        "canUseValidation" : 1,
        "classCount" : 23,
        "sampleCount" : 480000
      }
    },
    "dataSourceID" : "EF1F0974-3CC7-423B-B907-872B7C9165B6",
    "dataURL" : "file:///Users/feiyu/Desktop/CodeTextClassifier/data/train_create_ml.csv",
    "itemsCount" : 480000
  },
  "dataURL" : "file:///Users/feiyu/Desktop/CodeTextClassifier/data/train_create_ml.csv",
  "experimentIDs" : [
    "FA7B95E1-4163-479C-84B2-8569D73538F8",
    "F40D3C91-B748-42F3-8E90-A8F5A3603AD8"
  ],
  "id" : "EF1F0974-3CC7-423B-B907-872B7C9165B6",
  "modifiedDate" : "2026-06-25T09:33:29Z",
  "pathType" : 0,
  "preferredFilename" : "train_create_ml.csv",
  "title" : "train_create_ml.csv",
  "version" : "1.0"
}